upright_nhp/fiducials.py
upright_nhp/geometry.py
upright_nhp/query.py
upright_nhp/upright.py
upright_nhp-0.0.2.dist-info/LICENSE
upright_nhp-0.0.2.dist-info/METADATA
upright_nhp-0.0.2.dist-info/WHEEL
upright_nhp-0.0.2.dist-info/top_level.txt
upright_nhp-0.0.2.dist-info/RECORD
