Metadata-Version: 2.1
Name: upright-nhp
Version: 0.0.2
Summary: Upright non-human primate morphologies.
Author-email: Sarah Walling-Bell <sarah.wallingbell@alleninstitute.org>
Project-URL: Homepage, https://github.com/sarahwallingbell/upright_nhp.git
Requires-Python: >=3.9
License-File: LICENSE
Requires-Dist: numpy
Requires-Dist: pandas
Requires-Dist: scipy
Requires-Dist: neuron-morphology
Requires-Dist: morph-utils
